{
  "group_id": "4kKh0sk1QpSvjPE6p8VNKA",
  "season_id": "iFDXNJN8Tc2a4tii7kZxQg",
  "round_date": "2024-04-20",
  "scores_override": true,
  "submitted_at": "2024-04-20T12:00:00.000Z",
  "source_app": "glide",
  "external_event_id": "JncEPfo1TQGMUVK3fkK.2w",
  "scores": [
    {
      "source_player_ref": "mGOrrykGEwNu44EBsj0z",
      "source_player_name": "Scott",
      "score_value": -2,
      "source_email": "scottroseman@outlook.com",
      "source_venmo_handle": "Scott-Roseman-2",
      "source_is_active": true
    },
    {
      "source_player_ref": "YytMRmEEFc5bFdo6vPMA",
      "source_player_name": "Colm",
      "score_value": 2,
      "source_email": "colm.moran8@gmail.com",
      "source_venmo_handle": "ColmMoran",
      "source_is_active": true
    }
  ]
}